ltv_mpc/__init__.py
ltv_mpc/exceptions.py
ltv_mpc/mpc_problem.py
ltv_mpc/mpc_qp.py
ltv_mpc/plan.py
ltv_mpc/solve_mpc.py
ltv_mpc/live_plots/__init__.py
ltv_mpc/live_plots/cart_pole_plot.py
ltv_mpc/live_plots/live_plot.py
ltv_mpc/systems/__init__.py
ltv_mpc/systems/cart_pole.py
ltv_mpc-2.0.0.dist-info/LICENSE
ltv_mpc-2.0.0.dist-info/WHEEL
ltv_mpc-2.0.0.dist-info/METADATA
ltv_mpc-2.0.0.dist-info/RECORD
