Metadata-Version: 2.1
Name: ltv-mpc
Version: 2.0.0
Summary: Linear time-variant model predictive control in Python.
Keywords: model,predictive,control,linear,time-varying
Author-email: Stéphane Caron <stephane.caron@normalesup.org>
Maintainer-email: Stéphane Caron <stephane.caron@normalesup.org>
Requires-Python: >=3.8
Classifier: Development Status :: 5 - Production/Stable
Classifier: Intended Audience :: Developers
Classifier: Intended Audience :: Science/Research
Classifier: License :: OSI Approved :: Apache Software License
Classifier: Operating System :: OS Independent
Classifier: Programming Language :: Python :: 3
Classifier: Programming Language :: Python :: 3.8
Classifier: Programming Language :: Python :: 3.9
Classifier: Topic :: Scientific/Engineering :: Mathematics
Requires-Dist: qpsolvers >=1.8.0
Requires-Dist: sphinx ; extra == "doc"
Project-URL: Changelog, https://github.com/tasts-robots/ltv-mpc/blob/main/CHANGELOG.md
Project-URL: Documentation, https://tasts-robots.org/doc/ltv-mpc/
Project-URL: Source, https://github.com/tasts-robots/ltv-mpc
Project-URL: Tracker, https://github.com/tasts-robots/ltv-mpc/issues
Provides-Extra: doc
